README.md
license.txt
setup.cfg
setup.py
TearRouting/__init__.py
TearRouting/main.py
TearRouting.egg-info/PKG-INFO
TearRouting.egg-info/SOURCES.txt
TearRouting.egg-info/dependency_links.txt
TearRouting.egg-info/requires.txt
TearRouting.egg-info/top_level.txt
TearRouting/router/__init__.py
TearRouting/router/inner.py
TearRouting/router/manual/error.py
TearRouting/router/manual/functions.py
TearRouting/router/methods/__init__.py
TearRouting/router/methods/chat.py
TearRouting/router/methods/cos.py
TearRouting/router/methods/embed.py
TearRouting/router/methods/route.py
TearRouting/router/methods/training.py
TearRouting/router/__init__.py
TearRouting/router/inner.py
TearRouting/router/manual/error.py
TearRouting/router/manual/functions.py
TearRouting/router/methods/__init__.py
TearRouting/router/methods/chat.py
TearRouting/router/methods/cos.py
TearRouting/router/methods/embed.py
TearRouting/router/methods/route.py
TearRouting/router/methods/training.py