Metadata-Version: 2.1
Name: TearRouting
Version: 1.1
Summary: Trainable, efficient, autonomous routing.
Home-page: https://github.com/kesile/tear
Download-URL: https://github.com/kesile/tear/archive/refs/tags/publish.tar.gz
Author: John Kessler
Author-email: johncolekessler@gmail.com
License: MIT
Keywords: OpenAI,Routing,Router
Classifier: Development Status :: 3 - Alpha
Classifier: Intended Audience :: Developers
Classifier: Topic :: Software Development :: Build Tools
Classifier: License :: OSI Approved :: MIT License
Classifier: Programming Language :: Python :: 3
Classifier: Programming Language :: Python :: 3.4
Classifier: Programming Language :: Python :: 3.5
Classifier: Programming Language :: Python :: 3.6
Classifier: Programming Language :: Python :: 3.7
Classifier: Programming Language :: Python :: 3.8
Classifier: Programming Language :: Python :: 3.9
Classifier: Programming Language :: Python :: 3.10
License-File: license.txt
